mdalib/__init__.py
mdalib/pubsub.py
mdalib/test.py
mdalib-0.1.8.dist-info/LICENSE.txt
mdalib-0.1.8.dist-info/METADATA
mdalib-0.1.8.dist-info/WHEEL
mdalib-0.1.8.dist-info/top_level.txt
mdalib-0.1.8.dist-info/RECORD
