Metadata-Version: 2.1
Name: mdalib
Version: 0.1.8
Summary: ทดสอบ
Home-page: UNKNOWN
Author: Krit Naja
License: MIT
Download-URL: https://pypi.org/project/mdalib/
Keywords: MDA,kafka
Platform: UNKNOWN
Requires-Dist: kafka-python
Requires-Dist: msgpack
Requires-Dist: requests
